drawvec/__init__.py
drawvec/draw.py
PrimeLA-0.1.2.dist-info/LICENSE
PrimeLA-0.1.2.dist-info/METADATA
PrimeLA-0.1.2.dist-info/WHEEL
PrimeLA-0.1.2.dist-info/top_level.txt
PrimeLA-0.1.2.dist-info/RECORD
