Metadata-Version: 2.1
Name: PrimeLA
Version: 0.1.2
Summary: A small linear algebra visualization package
Home-page: https://github.com/dknife/PrimeLA
Author: dknife
Author-email: young.min.kang@gmail.com
License: UNKNOWN
Project-URL: Bug Tracker, https://github.com/dknife/PrimeLA
Platform: UNKNOWN
Classifier: Programming Language :: Python :: 3
Classifier: License :: OSI Approved :: MIT License
Classifier: Operating System :: OS Independent
Requires-Python: >=3.6
License-File: LICENSE
